stata_mcp_sdk/__init__.py
stata_mcp_sdk/__main__.py
stata_mcp_sdk/_client.py
stata_mcp_sdk/_version.py
stata_mcp_sdk/cli/__init__.py
stata_mcp_sdk/cli/_cli.py
stata_mcp_sdk/exceptions/__init__.py
stata_mcp_sdk/types/__init__.py
stata_mcp_sdk-0.1.0.dist-info/METADATA
stata_mcp_sdk-0.1.0.dist-info/WHEEL
stata_mcp_sdk-0.1.0.dist-info/entry_points.txt
stata_mcp_sdk-0.1.0.dist-info/licenses/LICENSE
stata_mcp_sdk-0.1.0.dist-info/RECORD
