Metadata-Version: 2.4
Name: stata-mcp-sdk
Version: 0.1.0
Summary: Let everyone make Stata-MCP powerful.
Project-URL: Homepage, https://www.sdk.statamcp.com
Project-URL: Source, https://github.com/sepinetam/stata-mcp-sdk
Author-email: SongTan <sepinetam@gmail.com>
License: Apache-2.0
License-File: LICENSE
Requires-Python: >=3.11
Requires-Dist: fastapi>=0.116.1
Requires-Dist: httpx>=0.28.1
